handylib/__init__.py
handylib/file_system.py
handylib/tools.py
handylib/utils.py
handy_library-0.0.7.dist-info/LICENCE.md
handy_library-0.0.7.dist-info/METADATA
handy_library-0.0.7.dist-info/WHEEL
handy_library-0.0.7.dist-info/top_level.txt
handy_library-0.0.7.dist-info/RECORD
