Metadata-Version: 2.1
Name: handy-library
Version: 0.0.7
Summary: A library that makes it very convenient to perform standard actions in Python
Author-email: SVJA7IK <svja7ik@gmail.com>
Project-URL: Homepage, https://github.com/SVJA7IK/HandyLibrary
Keywords: handy library,handylib,universal library
Classifier: License :: OSI Approved :: MIT License
Classifier: Programming Language :: Python
Classifier: Programming Language :: Python :: 3.10
Requires-Python: >=3.10
License-File: LICENCE.md
Requires-Dist: loguru ==0.7.2 ; python_version >= "3.10"
Requires-Dist: rich ==13.5.3 ; python_version >= "3.10"
